env_diff-0.4.dist-info/DESCRIPTION.rst
env_diff-0.4.dist-info/METADATA
env_diff-0.4.dist-info/RECORD
env_diff-0.4.dist-info/WHEEL
env_diff-0.4.dist-info/entry_points.txt
env_diff-0.4.dist-info/metadata.json
env_diff-0.4.dist-info/top_level.txt
envdiff/__init__.py
envdiff/__main__.py
envdiff/cli.py
envdiff/gui.py
envdiff/models.py
envdiff/utils.py
envdiff/tests/__init__.py
envdiff/tests/conftest.py
envdiff/tests/test_models.py
envdiff/tests/test_utils.py
tests/__init__.py
tests/conftest.py
tests/test_cli.py
