Metadata-Version: 2.0
Name: env-diff
Version: 0.4
Summary: Compares expected environment variables to those set in production.
Home-page: https://github.com/jacebrowning/env-diff
Author: Jace Browning
Author-email: jacebrowning@gmail.com
License: GNU General Public License v3 (GPLv3)
Platform: UNKNOWN
Classifier: Development Status :: 3 - Alpha
Classifier: Environment :: Console
Classifier: Intended Audience :: Developers
Classifier: Operating System :: OS Independent
Classifier: Programming Language :: Python
Classifier: Programming Language :: Python :: 3
Classifier: Programming Language :: Python :: 3.6
Classifier: License :: OSI Approved :: GNU General Public License v3 (GPLv3)
Classifier: Topic :: Software Development :: Quality Assurance
Classifier: Topic :: System :: Installation/Setup
Classifier: Topic :: System :: Systems Administration
Classifier: Topic :: Utilities
Requires-Dist: YORM (~=1.4)
Requires-Dist: blindspin (~=2.0.1)
Requires-Dist: click (~=6.7)
Requires-Dist: crayons (==0.1.2)
Requires-Dist: delegator.py (==0.0.8)
